README.rst
setup.py
maxmindupdater/__init__.py
maxmindupdater/__main__.py
maxmindupdater.egg-info/PKG-INFO
maxmindupdater.egg-info/SOURCES.txt
maxmindupdater.egg-info/dependency_links.txt
maxmindupdater.egg-info/entry_points.txt
maxmindupdater.egg-info/requires.txt
maxmindupdater.egg-info/top_level.txt